{
  "items": [
    {
      "title": "Panier Mini Hammam",
      "price": "11€",
      "badge": "Idéal cadeau Henna Day",
      "delay": "Délai : 2 semaines maximum",
      "image": "/images/panier_mini.jpeg",
      "images": [
        "/images/panier_mini.jpeg"
      ],
      "order": 1,
      "composition": [
        "Petit seau en cuivre",
        "Mini flacon fleur d'oranger",
        "2 mini flacons verre (roses séchées + henné)",
        "Rouge à lèvres marocain 24h",
        "Mini sucre marocain décoré henné",
        "Carte personnalisée Perle de Fès"
      ],
      "whatsappMessage": "Bonjour, je suis intéressée par le Panier Mini Hammam à 11€."
    },
    {
      "title": "Panier Essentiel Hammam",
      "price": "35€",
      "badge": "Personnalisation possible",
      "delay": "Délai : 2 semaines maximum",
      "image": "/images/panier_essentiel.jpeg",
      "images": [
        "/images/panier_essentiel.jpeg"
      ],
      "order": 2,
      "composition": [
        "Seau moyen en cuivre",
        "Foulard Zif Hayati",
        "Kessa — gant de gommage traditionnel",
        "Savon noir marocain au choix (classique / nila / aker fassi)",
        "Eau de rose",
        "Huile au choix 30ml (coco / argan)",
        "Aker Fassi",
        "Rouge à lèvres marocain 24h",
        "Pochette élégante brodée"
      ],
      "whatsappMessage": "Bonjour, je suis intéressée par le Panier Essentiel Hammam à 35€."
    },
    {
      "title": "Panier Premium Hammam",
      "price": "55€",
      "badge": "Idéal future mariée",
      "delay": "Délai : 2 semaines maximum",
      "image": "/images/panier_premium.jpeg",
      "images": [
        "/images/panier_premium.jpeg"
      ],
      "order": 3,
      "composition": [
        "Grand seau en cuivre",
        "Tous les produits du Panier Essentiel",
        "Mini bol en cuivre",
        "Pochette élégante brodée",
        "Encens Saghrina de Fès avec mabkhara",
        "Spray oud pour le corps",
        "Petite serviette brodée",
        "Foulard \"Madame la Mariée\" en arabe ou simple",
        "Personnalisation complète possible — Sur devis"
      ],
      "whatsappMessage": "Bonjour, je suis intéressée par le Panier Premium Hammam à 55€."
    },
    {
      "title": "Dragées Marocaines Orientales",
      "price": "À partir de 1,50€/pièce",
      "badge": "Prix adapté selon quantité",
      "delay": "Délai : 2 à 3 semaines",
      "image": "/images/dragees.jpeg",
      "images": [
        "/images/dragees.jpeg",
        "/images/dragees_2.jpeg",
        "/images/dragees_3.jpeg",
        "/images/dragees_4.jpeg",
        "/images/dragees_5.jpeg",
        "/images/dragees_6.jpeg",
        "/images/dragees_7.jpeg"
      ],
      "order": 4,
      "composition": [
        "Dragées marocaines orientales — tous modèles",
        "Vendues vides ou remplies au choix",
        "Personnalisation : prénom, date, couleur",
        "Prix dégressif selon quantité",
        "Minimum 20 pièces"
      ],
      "whatsappMessage": "Bonjour, je suis intéressée par les Dragées Marocaines Orientales."
    },
    {
      "title": "Papeterie Personnalisée",
      "price": "À partir de 1,50€/pièce",
      "badge": "Modèles sur demande",
      "delay": "Délai : 2 à 3 semaines",
      "image": "/images/papeterie.jpeg",
      "images": [
        "/images/papeterie.jpeg",
        "/images/papeterie_2.jpeg"
      ],
      "order": 5,
      "composition": [
        "Tout type de papeterie souhaitée sur demande",
        "Cartes de remerciement — minimum 10 pièces",
        "Cartes d'invitation mariage / henné — minimum 25 pièces",
        "Menus personnalisés",
        "Tous modèles disponibles — personnalisation complète",
        "Texte en français, en arabe ou bilingue",
        "Prix dégressif selon quantité",
        "Enveloppes disponibles sur demande"
      ],
      "whatsappMessage": "Bonjour, je suis intéressée par la Papeterie Personnalisée."
    }
  ]
}
